<?xml version="1.0" encoding="utf-8"?>
	<annotation>
		<folder>habitat</folder>
		<filename>004236.jpg</filename>
		<path>/lcc</path>
		<source>
			<database>Unknown</database>
		</source>
		<size>
			<width>295</width>
			<height>211</height>
			<depth>3</depth>
		</size>
		<segmented>0</segmented>
		<object>
			<name>tiger</name>
			<pose>0</pose>
			<truncated>0</truncated>
			<difficult>0</difficult>
			<bndbox>
				<xmin>48</xmin>
				<ymin>139</ymin>
				<xmax>114</xmax>
				<ymax>200</ymax>
			</bndbox>
		</object>
		<object>
			<name>bear</name>
			<pose>0</pose>
			<truncated>0</truncated>
			<difficult>0</difficult>
			<bndbox>
				<xmin>75</xmin>
				<ymin>6</ymin>
				<xmax>132</xmax>
				<ymax>74</ymax>
			</bndbox>
		</object>
		<object>
			<name>crocodile</name>
			<pose>0</pose>
			<truncated>0</truncated>
			<difficult>0</difficult>
			<bndbox>
				<xmin>136</xmin>
				<ymin>94</ymin>
				<xmax>205</xmax>
				<ymax>153</ymax>
			</bndbox>
		</object>
	</annotation>
